natasha/__init__.py
natasha/const.py
natasha/doc.py
natasha/emb.py
natasha/extractors.py
natasha/ner.py
natasha/norm.py
natasha/obj.py
natasha/record.py
natasha/segment.py
natasha/shape.py
natasha/span.py
natasha/syntax.py
natasha/data/__init__.py
natasha/data/dict/first.txt
natasha/data/dict/last.txt
natasha/data/dict/maybe_first.txt
natasha/data/emb/navec_news_v1_1B_250K_300d_100q.tar
natasha/data/model/slovnet_morph_news_v1.tar
natasha/data/model/slovnet_ner_news_v1.tar
natasha/data/model/slovnet_syntax_news_v1.tar
natasha/grammars/__init__.py
natasha/grammars/addr.py
natasha/grammars/date.py
natasha/grammars/money.py
natasha/grammars/name.py
natasha/morph/__init__.py
natasha/morph/lemma.py
natasha/morph/tagger.py
natasha/morph/vocab.py
natasha-1.6.0.dist-info/AUTHORS.md
natasha-1.6.0.dist-info/LICENSE
natasha-1.6.0.dist-info/METADATA
natasha-1.6.0.dist-info/WHEEL
natasha-1.6.0.dist-info/top_level.txt
natasha-1.6.0.dist-info/RECORD
