Metadata-Version: 2.1
Name: natasha
Version: 1.6.0
Summary: Named-entity recognition for russian language
Home-page: https://github.com/natasha/natasha
Author: Natasha contributors
Author-email: d.a.veselov@yandex.ru, alex@alexkuk.ru
License: MIT
Keywords: natural language processing,russian
Classifier: License :: OSI Approved :: MIT License
Classifier: Programming Language :: Python :: 3
Classifier: Topic :: Scientific/Engineering :: Artificial Intelligence
Classifier: Topic :: Text Processing :: Linguistic
License-File: LICENSE
License-File: AUTHORS.md
